[
  {
    "ID": 1,
    "Type": 1,
    "FirstName": "Mark",
    "MiddleName": "J",
    "LastName": "Williams",
    "TeamName": "",
    "TeamNumber": 0,
    "TeamSeason": 0,
    "ShortName": "M J Williams",
    "Nationality": "Wales",
    "Sex": "M",
    "BioPage": "https://snooker.org/plr/bio/mwilliams.shtml",
    "Born": "1975-03-21",
    "Twitter": "markwil147",
    "SurnameFirst": false,
    "License": "",
    "Club": "",
    "URL": "",
    "Photo": "https://snooker.org/img/players/MarkWilliams.png",
    "PhotoSource": "",
    "FirstSeasonAsPro": 1992,
    "LastSeasonAsPro": 0,
    "Info": "",
    "NumRankingTitles": 26,
    "NumMaximums": 3,
    "Died": ""
  },
  {
    "ID": 2,
    "Type": 1,
    "FirstName": "Stephen",
    "MiddleName": "",
    "LastName": "Maguire",
    "TeamName": "",
    "TeamNumber": 0,
    "TeamSeason": 0,
    "ShortName": "",
    "Nationality": "Scotland",
    "Sex": "M",
    "BioPage": "",
    "Born": "1981-03-13",
    "Twitter": "",
    "SurnameFirst": false,
    "License": "",
    "Club": "",
    "URL": "",
    "Photo": "https://snooker.org/img/players/Maguire.png",
    "PhotoSource": "",
    "FirstSeasonAsPro": 1998,
    "LastSeasonAsPro": 0,
    "Info": "",
    "NumRankingTitles": 6,
    "NumMaximums": 3,
    "Died": ""
  },
  {
    "ID": 4,
    "Type": 1,
    "FirstName": "Marco",
    "MiddleName": "",
    "LastName": "Fu",
    "TeamName": "",
    "TeamNumber": 0,
    "TeamSeason": 0,
    "ShortName": "Marco Fu",
    "Nationality": "Hong Kong",
    "Sex": "M",
    "BioPage": "",
    "Born": "1978-01-08",
    "Twitter": "Marcofu18",
    "SurnameFirst": false,
    "License": "",
    "Club": "",
    "URL": "",
    "Photo": "https://snooker.org/img/players/mfu.jpg",
    "PhotoSource": "",
    "FirstSeasonAsPro": 1998,
    "LastSeasonAsPro": 0,
    "Info": "",
    "NumRankingTitles": 3,
    "NumMaximums": 5,
    "Died": ""
  },
  {
    "ID": 5,
    "Type": 1,
    "FirstName": "Ronnie",
    "MiddleName": "",
    "LastName": "O'Sullivan",
    "TeamName": "",
    "TeamNumber": 0,
    "TeamSeason": 0,
    "ShortName": "R O'Sullivan",
    "Nationality": "England",
    "Sex": "M",
    "BioPage": "https://snooker.org/plr/bio/rosullivan.shtml",
    "Born": "1975-12-05",
    "Twitter": "ronnieo147",
    "SurnameFirst": false,
    "License": "",
    "Club": "",
    "URL": "https://www.facebook.com/TheRealRonnieOSullivan",
    "Photo": "https://snooker.org/img/players/rosullivan.jpg",
    "PhotoSource": "",
    "FirstSeasonAsPro": 1992,
    "LastSeasonAsPro": 0,
    "Info": "Class of '92, OBE (2016)",
    "NumRankingTitles": 41,
    "NumMaximums": 15,
    "Died": ""
  },
  {
    "ID": 8,
    "Type": 1,
    "FirstName": "Tom",
    "MiddleName": "",
    "LastName": "Ford",
    "TeamName": "",
    "TeamNumber": 0,
    "TeamSeason": 0,
    "ShortName": "",
    "Nationality": "England",
    "Sex": "M",
    "BioPage": "",
    "Born": "1983-08-17",
    "Twitter": "",
    "SurnameFirst": false,
    "License": "",
    "Club": "",
    "URL": "",
    "Photo": "https://snooker.org/img/players/TomFord.png",
    "PhotoSource": "",
    "FirstSeasonAsPro": 2001,
    "LastSeasonAsPro": 0,
    "Info": "",
    "NumRankingTitles": 0,
    "NumMaximums": 5,
    "Died": ""
  },
  {
    "ID": 9,
    "Type": 1,
    "FirstName": "Matthew",
    "MiddleName": "",
    "LastName": "Stevens",
    "TeamName": "",
    "TeamNumber": 0,
    "TeamSeason": 0,
    "ShortName": "M Stevens",
    "Nationality": "Wales",
    "Sex": "M",
    "BioPage": "",
    "Born": "1977-09-11",
    "Twitter": "MattStevens147",
    "SurnameFirst": false,
    "License": "",
    "Club": "",
    "URL": "",
    "Photo": "https://snooker.org/img/players/Stevens.png",
    "PhotoSource": "",
    "FirstSeasonAsPro": 1994,
    "LastSeasonAsPro": 0,
    "Info": "",
    "NumRankingTitles": 1,
    "NumMaximums": 1,
    "Died": ""
  },
  {
    "ID": 10,
    "Type": 1,
    "FirstName": "Jamie",
    "MiddleName": "",
    "LastName": "Jones",
    "TeamName": "",
    "TeamNumber": 0,
    "TeamSeason": 0,
    "ShortName": "Jamie Jones",
    "Nationality": "Wales",
    "Sex": "M",
    "BioPage": "",
    "Born": "1988-02-14",
    "Twitter": "",
    "SurnameFirst": false,
    "License": "",
    "Club": "",
    "URL": "facebook.com/thejoneskid147",
    "Photo": "https://snooker.org/img/players/Jamie Jones.png",
    "PhotoSource": "",
    "FirstSeasonAsPro": 2006,
    "LastSeasonAsPro": 0,
    "Info": "",
    "NumRankingTitles": 0,
    "NumMaximums": 1,
    "Died": ""
  },
  {
    "ID": 12,
    "Type": 1,
    "FirstName": "Judd",
    "MiddleName": "",
    "LastName": "Trump",
    "TeamName": "",
    "TeamNumber": 0,
    "TeamSeason": 0,
    "ShortName": "Judd Trump",
    "Nationality": "England",
    "Sex": "M",
    "BioPage": "",
    "Born": "1989-08-20",
    "Twitter": "juddtrump",
    "SurnameFirst": false,
    "License": "",
    "Club": "",
    "URL": "facebook.com/juddtrump147",
    "Photo": "https://snooker.org/img/players/jtrump.jpg",
    "PhotoSource": "",
    "FirstSeasonAsPro": 2005,
    "LastSeasonAsPro": 0,
    "Info": "",
    "NumRankingTitles": 29,
    "NumMaximums": 8,
    "Died": ""
  },
  {
    "ID": 15,
    "Type": 1,
    "FirstName": "Mark",
    "MiddleName": "",
    "LastName": "Davis",
    "TeamName": "",
    "TeamNumber": 0,
    "TeamSeason": 0,
    "ShortName": "Mark Davis",
    "Nationality": "England",
    "Sex": "M",
    "BioPage": "",
    "Born": "1972-08-12",
    "Twitter": "markdavis2108",
    "SurnameFirst": false,
    "License": "",
    "Club": "",
    "URL": "",
    "Photo": "https://snooker.org/img/players/MarkDavis.png",
    "PhotoSource": "",
    "FirstSeasonAsPro": 1991,
    "LastSeasonAsPro": 0,
    "Info": "",
    "NumRankingTitles": 0,
    "NumMaximums": 2,
    "Died": ""
  },
  {
    "ID": 16,
    "Type": 1,
    "FirstName": "Barry",
    "MiddleName": "",
    "LastName": "Hawkins",
    "TeamName": "",
    "TeamNumber": 0,
    "TeamSeason": 0,
    "ShortName": "",
    "Nationality": "England",
    "Sex": "M",
    "BioPage": "",
    "Born": "1979-04-23",
    "Twitter": "",
    "SurnameFirst": false,
    "License": "",
    "Club": "",
    "URL": "",
    "Photo": "https://snooker.org/img/players/bhawkins.jpg",
    "PhotoSource": "",
    "FirstSeasonAsPro": 1996,
    "LastSeasonAsPro": 0,
    "Info": "",
    "NumRankingTitles": 4,
    "NumMaximums": 3,
    "Died": ""
  },
  {
    "ID": 17,
    "Type": 1,
    "FirstName": "Mark",
    "MiddleName": "",
    "LastName": "Selby",
    "TeamName": "",
    "TeamNumber": 0,
    "TeamSeason": 0,
    "ShortName": "",
    "Nationality": "England",
    "Sex": "M",
    "BioPage": "",
    "Born": "1983-06-19",
    "Twitter": "markjesterselby",
    "SurnameFirst": false,
    "License": "",
    "Club": "",
    "URL": "markselby.info",
    "Photo": "https://snooker.org/img/players/mselby.jpg",
    "PhotoSource": "",
    "FirstSeasonAsPro": 1999,
    "LastSeasonAsPro": 0,
    "Info": "",
    "NumRankingTitles": 23,
    "NumMaximums": 5,
    "Died": ""
  },
  {
    "ID": 19,
    "Type": 1,
    "FirstName": "Ben",
    "MiddleName": "",
    "LastName": "Woollaston",
    "TeamName": "",
    "TeamNumber": 0,
    "TeamSeason": 0,
    "ShortName": "",
    "Nationality": "England",
    "Sex": "M",
    "BioPage": "",
    "Born": "1987-05-14",
    "Twitter": "ben_Woollaston",
    "SurnameFirst": false,
    "License": "",
    "Club": "",
    "URL": "",
    "Photo": "https://snooker.org/img/players/Woollaston.png",
    "PhotoSource": "",
    "FirstSeasonAsPro": 2003,
    "LastSeasonAsPro": 0,
    "Info": "",
    "NumRankingTitles": 0,
    "NumMaximums": 1,
    "Died": ""
  },
  {
    "ID": 20,
    "Type": 1,
    "FirstName": "Jimmy",
    "MiddleName": "",
    "LastName": "White",
    "TeamName": "",
    "TeamNumber": 0,
    "TeamSeason": 0,
    "ShortName": "J White",
    "Nationality": "England",
    "Sex": "M",
    "BioPage": "https://snooker.org/plr/bio/jwhite.shtml",
    "Born": "1962-05-02",
    "Twitter": "jimmywhite147",
    "SurnameFirst": false,
    "License": "",
    "Club": "",
    "URL": "jimmywhitesnooker.com",
    "Photo": "https://snooker.org/img/players/Jimmy White.png",
    "PhotoSource": "",
    "FirstSeasonAsPro": 1980,
    "LastSeasonAsPro": 0,
    "Info": "He was one of a group of players known as the <i>Magnificent Seven</i> managed by Henry West, the others being <a href='https://www.snooker.org/res/index.asp?player=469&season=-1'>Joe Johnson</a>, <a href='https://www.snooker.org/res/index.asp?player=3702&season=-1'>Terry Whitthread</a>, <a href='https://www.snooker.org/res/index.asp?player=796&season=-1'>Patsy Fagan</a>, <a href='https://www.snooker.org/res/index.asp?player=3484&season=-1'>John Virgo</a>, <a href='https://www.snooker.org/res/index.asp?player=181&season=-1'>Tony Knowles</a>, and <a href='https://www.snooker.org/res/index.asp?player=2874&season=-1'>Tony Meo</a>.",
    "NumRankingTitles": 10,
    "NumMaximums": 1,
    "Died": ""
  },
  {
    "ID": 21,
    "Type": 1,
    "FirstName": "Alfie",
    "MiddleName": "",
    "LastName": "Burden",
    "TeamName": "",
    "TeamNumber": 0,
    "TeamSeason": 0,
    "ShortName": "",
    "Nationality": "England",
    "Sex": "M",
    "BioPage": "",
    "Born": "1976-12-14",
    "Twitter": "Aboflondon4",
    "SurnameFirst": false,
    "License": "",
    "Club": "",
    "URL": "",
    "Photo": "https://snooker.org/img/players/Burden.png",
    "PhotoSource": "",
    "FirstSeasonAsPro": 1994,
    "LastSeasonAsPro": 0,
    "Info": "",
    "NumRankingTitles": 0,
    "NumMaximums": 1,
    "Died": ""
  },
  {
    "ID": 22,
    "Type": 1,
    "FirstName": "Anthony",
    "MiddleName": "",
    "LastName": "McGill",
    "TeamName": "",
    "TeamNumber": 0,
    "TeamSeason": 0,
    "ShortName": "",
    "Nationality": "Scotland",
    "Sex": "M",
    "BioPage": "",
    "Born": "1991-02-05",
    "Twitter": "",
    "SurnameFirst": false,
    "License": "",
    "Club": "",
    "URL": "",
    "Photo": "https://snooker.org/img/players/McGill.png",
    "PhotoSource": "",
    "FirstSeasonAsPro": 2010,
    "LastSeasonAsPro": 0,
    "Info": "",
    "NumRankingTitles": 2,
    "NumMaximums": 0,
    "Died": ""
  },
  {
    "ID": 24,
    "Type": 1,
    "FirstName": "Guodong",
    "MiddleName": "",
    "LastName": "Xiao",
    "TeamName": "",
    "TeamNumber": 0,
    "TeamSeason": 0,
    "ShortName": "Xiao Guodong",
    "Nationality": "China",
    "Sex": "M",
    "BioPage": "",
    "Born": "1989-02-10",
    "Twitter": "",
    "SurnameFirst": true,
    "License": "",
    "Club": "",
    "URL": "",
    "Photo": "https://snooker.org/img/players/Xiao.png",
    "PhotoSource": "",
    "FirstSeasonAsPro": 2007,
    "LastSeasonAsPro": 0,
    "Info": "",
    "NumRankingTitles": 1,
    "NumMaximums": 1,
    "Died": ""
  },
  {
    "ID": 25,
    "Type": 1,
    "FirstName": "Andrew",
    "MiddleName": "",
    "LastName": "Higginson",
    "TeamName": "",
    "TeamNumber": 0,
    "TeamSeason": 0,
    "ShortName": "",
    "Nationality": "England",
    "Sex": "M",
    "BioPage": "",
    "Born": "1977-12-13",
    "Twitter": "",
    "SurnameFirst": false,
    "License": "",
    "Club": "",
    "URL": "",
    "Photo": "https://snooker.org/img/players/Higginson.png",
    "PhotoSource": "",
    "FirstSeasonAsPro": 1996,
    "LastSeasonAsPro": 0,
    "Info": "",
    "NumRankingTitles": 0,
    "NumMaximums": 1,
    "Died": ""
  },
  {
    "ID": 26,
    "Type": 1,
    "FirstName": "Allan",
    "MiddleName": "",
    "LastName": "Taylor",
    "TeamName": "",
    "TeamNumber": 0,
    "TeamSeason": 0,
    "ShortName": "A Taylor",
    "Nationality": "England",
    "Sex": "M",
    "BioPage": "",
    "Born": "1984-11-28",
    "Twitter": "",
    "SurnameFirst": false,
    "License": "",
    "Club": "",
    "URL": "",
    "Photo": "https://snooker.org/img/players/Allan Taylor.png",
    "PhotoSource": "",
    "FirstSeasonAsPro": 2013,
    "LastSeasonAsPro": 0,
    "Info": "",
    "NumRankingTitles": 0,
    "NumMaximums": 0,
    "Died": ""
  },
  {
    "ID": 27,
    "Type": 1,
    "FirstName": "Martin",
    "MiddleName": "",
    "LastName": "Gould",
    "TeamName": "",
    "TeamNumber": 0,
    "TeamSeason": 0,
    "ShortName": "",
    "Nationality": "England",
    "Sex": "M",
    "BioPage": "",
    "Born": "1981-09-14",
    "Twitter": "GouldyBalls147",
    "SurnameFirst": false,
    "License": "",
    "Club": "",
    "URL": "",
    "Photo": "https://snooker.org/img/players/Gould.png",
    "PhotoSource": "",
    "FirstSeasonAsPro": 2003,
    "LastSeasonAsPro": 0,
    "Info": "",
    "NumRankingTitles": 1,
    "NumMaximums": 1,
    "Died": ""
  },
  {
    "ID": 30,
    "Type": 1,
    "FirstName": "Stuart",
    "MiddleName": "",
    "LastName": "Bingham",
    "TeamName": "",
    "TeamNumber": 0,
    "TeamSeason": 0,
    "ShortName": "",
    "Nationality": "England",
    "Sex": "M",
    "BioPage": "",
    "Born": "1976-05-21",
    "Twitter": "Stuart__Bingham  ",
    "SurnameFirst": false,
    "License": "",
    "Club": "",
    "URL": "stuartbingham.com",
    "Photo": "https://snooker.org/img/players/Bingham.png",
    "PhotoSource": "",
    "FirstSeasonAsPro": 1995,
    "LastSeasonAsPro": 0,
    "Info": "",
    "NumRankingTitles": 6,
    "NumMaximums": 9,
    "Died": ""
  },
  {
    "ID": 32,
    "Type": 1,
    "FirstName": "Daniel",
    "MiddleName": "",
    "LastName": "Wells",
    "TeamName": "",
    "TeamNumber": 0,
    "TeamSeason": 0,
    "ShortName": "",
    "Nationality": "Wales",
    "Sex": "M",
    "BioPage": "",
    "Born": "1988-07-31",
    "Twitter": "",
    "SurnameFirst": false,
    "License": "",
    "Club": "",
    "URL": "",
    "Photo": "https://snooker.org/img/players/Wells.png",
    "PhotoSource": "",
    "FirstSeasonAsPro": 2008,
    "LastSeasonAsPro": 0,
    "Info": "",
    "NumRankingTitles": 0,
    "NumMaximums": 0,
    "Died": ""
  },
  {
    "ID": 33,
    "Type": 1,
    "FirstName": "Dominic",
    "MiddleName": "",
    "LastName": "Dale",
    "TeamName": "",
    "TeamNumber": 0,
    "TeamSeason": 0,
    "ShortName": "",
    "Nationality": "Wales",
    "Sex": "M",
    "BioPage": "",
    "Born": "1971-12-29",
    "Twitter": "",
    "SurnameFirst": false,
    "License": "",
    "Club": "",
    "URL": "",
    "Photo": "https://snooker.org/img/players/dale.png",
    "PhotoSource": "",
    "FirstSeasonAsPro": 1992,
    "LastSeasonAsPro": 0,
    "Info": "",
    "NumRankingTitles": 2,
    "NumMaximums": 0,
    "Died": ""
  },
  {
    "ID": 39,
    "Type": 1,
    "FirstName": "Kyren",
    "MiddleName": "",
    "LastName": "Wilson",
    "TeamName": "",
    "TeamNumber": 0,
    "TeamSeason": 0,
    "ShortName": "K Wilson",
    "Nationality": "England",
    "Sex": "M",
    "BioPage": "",
    "Born": "1991-12-23",
    "Twitter": "KyrenWilson",
    "SurnameFirst": false,
    "License": "",
    "Club": "",
    "URL": "",
    "Photo": "https://snooker.org/img/players/Kyren Wilson.png",
    "PhotoSource": "",
    "FirstSeasonAsPro": 2010,
    "LastSeasonAsPro": 0,
    "Info": "",
    "NumRankingTitles": 8,
    "NumMaximums": 5,
    "Died": ""
  },
  {
    "ID": 47,
    "Type": 1,
    "FirstName": "Matthew",
    "MiddleName": "",
    "LastName": "Selt",
    "TeamName": "",
    "TeamNumber": 0,
    "TeamSeason": 0,
    "ShortName": "",
    "Nationality": "England",
    "Sex": "M",
    "BioPage": "",
    "Born": "1985-03-07",
    "Twitter": "",
    "SurnameFirst": false,
    "License": "",
    "Club": "",
    "URL": "",
    "Photo": "https://snooker.org/img/players/Selt.png",
    "PhotoSource": "",
    "FirstSeasonAsPro": 2002,
    "LastSeasonAsPro": 0,
    "Info": "",
    "NumRankingTitles": 1,
    "NumMaximums": 0,
    "Died": ""
  },
  {
    "ID": 49,
    "Type": 1,
    "FirstName": "Mitchell",
    "MiddleName": "",
    "LastName": "Mann",
    "TeamName": "",
    "TeamNumber": 0,
    "TeamSeason": 0,
    "ShortName": "M Mann",
    "Nationality": "England",
    "Sex": "M",
    "BioPage": "",
    "Born": "1991-12-26",
    "Twitter": "MitchellSnooker",
    "SurnameFirst": false,
    "License": "",
    "Club": "",
    "URL": "",
    "Photo": "https://snooker.org/img/players/Mann.png",
    "PhotoSource": "",
    "FirstSeasonAsPro": 2014,
    "LastSeasonAsPro": 0,
    "Info": "",
    "NumRankingTitles": 0,
    "NumMaximums": 0,
    "Died": ""
  },
  {
    "ID": 52,
    "Type": 1,
    "FirstName": "Graeme",
    "MiddleName": "",
    "LastName": "Dott",
    "TeamName": "",
    "TeamNumber": 0,
    "TeamSeason": 0,
    "ShortName": "",
    "Nationality": "Scotland",
    "Sex": "M",
    "BioPage": "",
    "Born": "1977-05-12",
    "Twitter": "",
    "SurnameFirst": false,
    "License": "",
    "Club": "",
    "URL": "",
    "Photo": "https://snooker.org/img/players/Dott.png",
    "PhotoSource": "",
    "FirstSeasonAsPro": 1994,
    "LastSeasonAsPro": 0,
    "Info": "",
    "NumRankingTitles": 2,
    "NumMaximums": 2,
    "Died": ""
  },
  {
    "ID": 58,
    "Type": 1,
    "FirstName": "Jordan",
    "MiddleName": "",
    "LastName": "Brown",
    "TeamName": "",
    "TeamNumber": 0,
    "TeamSeason": 0,
    "ShortName": "J Brown",
    "Nationality": "Northern Ireland",
    "Sex": "M",
    "BioPage": "",
    "Born": "1987-10-09",
    "Twitter": "jordyb147",
    "SurnameFirst": false,
    "License": "",
    "Club": "",
    "URL": "",
    "Photo": "",
    "PhotoSource": "",
    "FirstSeasonAsPro": 2009,
    "LastSeasonAsPro": 0,
    "Info": "",
    "NumRankingTitles": 1,
    "NumMaximums": 0,
    "Died": ""
  },
  {
    "ID": 62,
    "Type": 1,
    "FirstName": "Ricky",
    "MiddleName": "",
    "LastName": "Walden",
    "TeamName": "",
    "TeamNumber": 0,
    "TeamSeason": 0,
    "ShortName": "",
    "Nationality": "England",
    "Sex": "M",
    "BioPage": "",
    "Born": "1982-11-11",
    "Twitter": "",
    "SurnameFirst": false,
    "License": "",
    "Club": "",
    "URL": "rickywalden.co.uk",
    "Photo": "https://snooker.org/img/players/Walden.png",
    "PhotoSource": "",
    "FirstSeasonAsPro": 2000,
    "LastSeasonAsPro": 0,
    "Info": "",
    "NumRankingTitles": 3,
    "NumMaximums": 1,
    "Died": ""
  },
  {
    "ID": 65,
    "Type": 1,
    "FirstName": "Andrew",
    "MiddleName": "",
    "LastName": "Pagett",
    "TeamName": "",
    "TeamNumber": 0,
    "TeamSeason": 0,
    "ShortName": "",
    "Nationality": "Wales",
    "Sex": "M",
    "BioPage": "",
    "Born": "1982-04-25",
    "Twitter": "AndrewPagett",
    "SurnameFirst": false,
    "License": "",
    "Club": "",
    "URL": "",
    "Photo": "",
    "PhotoSource": "",
    "FirstSeasonAsPro": 2003,
    "LastSeasonAsPro": 0,
    "Info": "",
    "NumRankingTitles": 0,
    "NumMaximums": 0,
    "Died": ""
  },
  {
    "ID": 67,
    "Type": 1,
    "FirstName": "David",
    "MiddleName": "",
    "LastName": "Grace",
    "TeamName": "",
    "TeamNumber": 0,
    "TeamSeason": 0,
    "ShortName": "",
    "Nationality": "England",
    "Sex": "M",
    "BioPage": "",
    "Born": "1985-05-05",
    "Twitter": "daveg147",
    "SurnameFirst": false,
    "License": "",
    "Club": "",
    "URL": "davidgracesnooker.co.uk",
    "Photo": "https://snooker.org/img/players/Grace.png",
    "PhotoSource": "",
    "FirstSeasonAsPro": 2008,
    "LastSeasonAsPro": 0,
    "Info": "",
    "NumRankingTitles": 0,
    "NumMaximums": 0,
    "Died": ""
  },
  {
    "ID": 68,
    "Type": 1,
    "FirstName": "Ryan",
    "MiddleName": "",
    "LastName": "Day",
    "TeamName": "",
    "TeamNumber": 0,
    "TeamSeason": 0,
    "ShortName": "R Day",
    "Nationality": "Wales",
    "Sex": "M",
    "BioPage": "",
    "Born": "1980-03-23",
    "Twitter": "ryan23day",
    "SurnameFirst": false,
    "License": "",
    "Club": "",
    "URL": "",
    "Photo": "https://snooker.org/img/players/Ryan Day.png",
    "PhotoSource": "",
    "FirstSeasonAsPro": 1998,
    "LastSeasonAsPro": 0,
    "Info": "",
    "NumRankingTitles": 4,
    "NumMaximums": 4,
    "Died": ""
  },
  {
    "ID": 81,
    "Type": 1,
    "FirstName": "Anda",
    "MiddleName": "",
    "LastName": "Zhang",
    "TeamName": "",
    "TeamNumber": 0,
    "TeamSeason": 0,
    "ShortName": "Zhang Anda",
    "Nationality": "China",
    "Sex": "M",
    "BioPage": "",
    "Born": "1991-12-25",
    "Twitter": "",
    "SurnameFirst": true,
    "License": "",
    "Club": "",
    "URL": "",
    "Photo": "https://snooker.org/img/players/Anda.png",
    "PhotoSource": "",
    "FirstSeasonAsPro": 2009,
    "LastSeasonAsPro": 0,
    "Info": "",
    "NumRankingTitles": 1,
    "NumMaximums": 3,
    "Died": ""
  },
  {
    "ID": 85,
    "Type": 1,
    "FirstName": "Jack",
    "MiddleName": "",
    "LastName": "Lisowski",
    "TeamName": "",
    "TeamNumber": 0,
    "TeamSeason": 0,
    "ShortName": "",
    "Nationality": "England",
    "Sex": "M",
    "BioPage": "",
    "Born": "1991-06-25",
    "Twitter": "JackLisowski",
    "SurnameFirst": false,
    "License": "",
    "Club": "",
    "URL": "",
    "Photo": "https://snooker.org/img/players/Lisowski.png",
    "PhotoSource": "",
    "FirstSeasonAsPro": 2010,
    "LastSeasonAsPro": 0,
    "Info": "",
    "NumRankingTitles": 0,
    "NumMaximums": 1,
    "Died": ""
  },
  {
    "ID": 87,
    "Type": 1,
    "FirstName": "Ian",
    "MiddleName": "",
    "LastName": "Burns",
    "TeamName": "",
    "TeamNumber": 0,
    "TeamSeason": 0,
    "ShortName": "I Burns",
    "Nationality": "England",
    "Sex": "M",
    "BioPage": "",
    "Born": "1985-03-11",
    "Twitter": "BurnsyIB",
    "SurnameFirst": false,
    "License": "",
    "Club": "",
    "URL": "",
    "Photo": "https://snooker.org/img/players/Burns.png",
    "PhotoSource": "",
    "FirstSeasonAsPro": 2012,
    "LastSeasonAsPro": 0,
    "Info": "",
    "NumRankingTitles": 0,
    "NumMaximums": 0,
    "Died": ""
  },
  {
    "ID": 89,
    "Type": 1,
    "FirstName": "Zak",
    "MiddleName": "",
    "LastName": "Surety",
    "TeamName": "",
    "TeamNumber": 0,
    "TeamSeason": 0,
    "ShortName": "",
    "Nationality": "England",
    "Sex": "M",
    "BioPage": "",
    "Born": "1991-10-04",
    "Twitter": "ZakSurety",
    "SurnameFirst": false,
    "License": "",
    "Club": "",
    "URL": "",
    "Photo": "https://snooker.org/img/players/Zak.png",
    "PhotoSource": "",
    "FirstSeasonAsPro": 2014,
    "LastSeasonAsPro": 0,
    "Info": "",
    "NumRankingTitles": 0,
    "NumMaximums": 1,
    "Died": ""
  },
  {
    "ID": 90,
    "Type": 1,
    "FirstName": "Jak",
    "MiddleName": "",
    "LastName": "Jones",
    "TeamName": "",
    "TeamNumber": 0,
    "TeamSeason": 0,
    "ShortName": "Jak Jones",
    "Nationality": "Wales",
    "Sex": "M",
    "BioPage": "",
    "Born": "1993-07-29",
    "Twitter": "JakJones147",
    "SurnameFirst": false,
    "License": "",
    "Club": "",
    "URL": "",
    "Photo": "",
    "PhotoSource": "",
    "FirstSeasonAsPro": 2010,
    "LastSeasonAsPro": 0,
    "Info": "",
    "NumRankingTitles": 0,
    "NumMaximums": 0,
    "Died": ""
  },
  {
    "ID": 92,
    "Type": 1,
    "FirstName": "Robert",
    "MiddleName": "",
    "LastName": "Milkins",
    "TeamName": "",
    "TeamNumber": 0,
    "TeamSeason": 0,
    "ShortName": "",
    "Nationality": "England",
    "Sex": "M",
    "BioPage": "",
    "Born": "1976-03-06",
    "Twitter": "robmilkins147",
    "SurnameFirst": false,
    "License": "",
    "Club": "",
    "URL": "",
    "Photo": "https://snooker.org/img/players/Milkins.png",
    "PhotoSource": "",
    "FirstSeasonAsPro": 1995,
    "LastSeasonAsPro": 0,
    "Info": "",
    "NumRankingTitles": 2,
    "NumMaximums": 3,
    "Died": ""
  },
  {
    "ID": 93,
    "Type": 1,
    "FirstName": "Jimmy",
    "MiddleName": "",
    "LastName": "Robertson",
    "TeamName": "",
    "TeamNumber": 0,
    "TeamSeason": 0,
    "ShortName": "J Robertson",
    "Nationality": "England",
    "Sex": "M",
    "BioPage": "",
    "Born": "1986-05-03",
    "Twitter": "",
    "SurnameFirst": false,
    "License": "",
    "Club": "",
    "URL": "",
    "Photo": "https://snooker.org/img/players/Jimmy Robertson.png",
    "PhotoSource": "",
    "FirstSeasonAsPro": 2002,
    "LastSeasonAsPro": 0,
    "Info": "",
    "NumRankingTitles": 1,
    "NumMaximums": 0,
    "Died": ""
  },
  {
    "ID": 96,
    "Type": 1,
    "FirstName": "Robbie",
    "MiddleName": "",
    "LastName": "Williams",
    "TeamName": "",
    "TeamNumber": 0,
    "TeamSeason": 0,
    "ShortName": "R Williams",
    "Nationality": "England",
    "Sex": "M",
    "BioPage": "",
    "Born": "1986-12-28",
    "Twitter": "",
    "SurnameFirst": false,
    "License": "",
    "Club": "",
    "URL": "",
    "Photo": "https://snooker.org/img/players/Robbie Williams.png",
    "PhotoSource": "",
    "FirstSeasonAsPro": 2012,
    "LastSeasonAsPro": 0,
    "Info": "",
    "NumRankingTitles": 0,
    "NumMaximums": 0,
    "Died": ""
  },
  {
    "ID": 97,
    "Type": 1,
    "FirstName": "Shaun",
    "MiddleName": "",
    "LastName": "Murphy",
    "TeamName": "",
    "TeamNumber": 0,
    "TeamSeason": 0,
    "ShortName": "S Murphy",
    "Nationality": "England",
    "Sex": "M",
    "BioPage": "",
    "Born": "1982-08-10",
    "Twitter": "Magician147",
    "SurnameFirst": false,
    "License": "",
    "Club": "",
    "URL": "shaunmurphy.net",
    "Photo": "https://snooker.org/img/players/Murphy.png",
    "PhotoSource": "",
    "FirstSeasonAsPro": 1998,
    "LastSeasonAsPro": 0,
    "Info": "",
    "NumRankingTitles": 12,
    "NumMaximums": 8,
    "Died": ""
  },
  {
    "ID": 101,
    "Type": 1,
    "FirstName": "Luca",
    "MiddleName": "",
    "LastName": "Brecel",
    "TeamName": "",
    "TeamNumber": 0,
    "TeamSeason": 0,
    "ShortName": "",
    "Nationality": "Belgium",
    "Sex": "M",
    "BioPage": "",
    "Born": "1995-03-08",
    "Twitter": "",
    "SurnameFirst": false,
    "License": "",
    "Club": "",
    "URL": "luca-brecel.com/",
    "Photo": "https://snooker.org/img/players/Brecel.png",
    "PhotoSource": "",
    "FirstSeasonAsPro": 2011,
    "LastSeasonAsPro": 0,
    "Info": "",
    "NumRankingTitles": 4,
    "NumMaximums": 1,
    "Died": ""
  },
  {
    "ID": 106,
    "Type": 1,
    "FirstName": "Jamie",
    "MiddleName": "",
    "LastName": "Clarke",
    "TeamName": "",
    "TeamNumber": 0,
    "TeamSeason": 0,
    "ShortName": "J Clarke",
    "Nationality": "Wales",
    "Sex": "M",
    "BioPage": "",
    "Born": "1994-10-05",
    "Twitter": "JamieClarkeReal",
    "SurnameFirst": false,
    "License": "",
    "Club": "",
    "URL": "",
    "Photo": "",
    "PhotoSource": "",
    "FirstSeasonAsPro": 2018,
    "LastSeasonAsPro": 0,
    "Info": "",
    "NumRankingTitles": 0,
    "NumMaximums": 0,
    "Died": ""
  },
  {
    "ID": 109,
    "Type": 1,
    "FirstName": "Sam",
    "MiddleName": "",
    "LastName": "Craigie",
    "TeamName": "",
    "TeamNumber": 0,
    "TeamSeason": 0,
    "ShortName": "Sam Craigie",
    "Nationality": "England",
    "Sex": "M",
    "BioPage": "",
    "Born": "1993-12-29",
    "Twitter": "",
    "SurnameFirst": false,
    "License": "",
    "Club": "",
    "URL": "",
    "Photo": "",
    "PhotoSource": "",
    "FirstSeasonAsPro": 2011,
    "LastSeasonAsPro": 0,
    "Info": "",
    "NumRankingTitles": 0,
    "NumMaximums": 0,
    "Died": ""
  },
  {
    "ID": 115,
    "Type": 1,
    "FirstName": "Anthony",
    "MiddleName": "",
    "LastName": "Hamilton",
    "TeamName": "",
    "TeamNumber": 0,
    "TeamSeason": 0,
    "ShortName": "",
    "Nationality": "England",
    "Sex": "M",
    "BioPage": "https://snooker.org/plr/bio/ahamilton.shtml",
    "Born": "1971-06-29",
    "Twitter": "",
    "SurnameFirst": false,
    "License": "",
    "Club": "",
    "URL": "",
    "Photo": "https://snooker.org/img/players/Hamilton.PNG",
    "PhotoSource": "",
    "FirstSeasonAsPro": 1991,
    "LastSeasonAsPro": 0,
    "Info": "",
    "NumRankingTitles": 1,
    "NumMaximums": 0,
    "Died": ""
  },
  {
    "ID": 118,
    "Type": 1,
    "FirstName": "David",
    "MiddleName": "",
    "LastName": "Gilbert",
    "TeamName": "",
    "TeamNumber": 0,
    "TeamSeason": 0,
    "ShortName": "D Gilbert",
    "Nationality": "England",
    "Sex": "M",
    "BioPage": "",
    "Born": "1981-06-12",
    "Twitter": "angryfarmer147",
    "SurnameFirst": false,
    "License": "",
    "Club": "",
    "URL": "",
    "Photo": "https://snooker.org/img/players/Gilbert.png",
    "PhotoSource": "",
    "FirstSeasonAsPro": 2002,
    "LastSeasonAsPro": 0,
    "Info": "",
    "NumRankingTitles": 1,
    "NumMaximums": 2,
    "Died": ""
  },
  {
    "ID": 120,
    "Type": 1,
    "FirstName": "Martin",
    "MiddleName": "",
    "LastName": "O'Donnell",
    "TeamName": "",
    "TeamNumber": 0,
    "TeamSeason": 0,
    "ShortName": "",
    "Nationality": "England",
    "Sex": "M",
    "BioPage": "",
    "Born": "1986-06-04",
    "Twitter": "TheMOD147",
    "SurnameFirst": false,
    "License": "",
    "Club": "",
    "URL": "",
    "Photo": "https://snooker.org/img/players/Martin O.PNG",
    "PhotoSource": "",
    "FirstSeasonAsPro": 2012,
    "LastSeasonAsPro": 0,
    "Info": "",
    "NumRankingTitles": 0,
    "NumMaximums": 0,
    "Died": ""
  },
  {
    "ID": 125,
    "Type": 1,
    "FirstName": "Michael",
    "MiddleName": "",
    "LastName": "Holt",
    "TeamName": "",
    "TeamNumber": 0,
    "TeamSeason": 0,
    "ShortName": "",
    "Nationality": "England",
    "Sex": "M",
    "BioPage": "",
    "Born": "1978-08-07",
    "Twitter": "HitmanHolt",
    "SurnameFirst": false,
    "License": "",
    "Club": "",
    "URL": "",
    "Photo": "https://snooker.org/img/players/Holt.png",
    "PhotoSource": "",
    "FirstSeasonAsPro": 1996,
    "LastSeasonAsPro": 0,
    "Info": "",
    "NumRankingTitles": 1,
    "NumMaximums": 0,
    "Died": ""
  },
  {
    "ID": 128,
    "Type": 1,
    "FirstName": "Stuart",
    "MiddleName": "",
    "LastName": "Carrington",
    "TeamName": "",
    "TeamNumber": 0,
    "TeamSeason": 0,
    "ShortName": "",
    "Nationality": "England",
    "Sex": "M",
    "BioPage": "",
    "Born": "1990-05-14",
    "Twitter": "",
    "SurnameFirst": false,
    "License": "",
    "Club": "",
    "URL": "",
    "Photo": "https://snooker.org/img/players/Carrington.png",
    "PhotoSource": "",
    "FirstSeasonAsPro": 2011,
    "LastSeasonAsPro": 0,
    "Info": "",
    "NumRankingTitles": 0,
    "NumMaximums": 0,
    "Died": ""
  },
  {
    "ID": 154,
    "Type": 1,
    "FirstName": "Neil",
    "MiddleName": "",
    "LastName": "Robertson",
    "TeamName": "",
    "TeamNumber": 0,
    "TeamSeason": 0,
    "ShortName": "N Robertson",
    "Nationality": "Australia",
    "Sex": "M",
    "BioPage": "",
    "Born": "1982-02-11",
    "Twitter": "nr147",
    "SurnameFirst": false,
    "License": "",
    "Club": "",
    "URL": "neilrobertson.net",
    "Photo": "https://snooker.org/img/players/NRobertson.png",
    "PhotoSource": "",
    "FirstSeasonAsPro": 1998,
    "LastSeasonAsPro": 0,
    "Info": "",
    "NumRankingTitles": 24,
    "NumMaximums": 5,
    "Died": ""
  },
  {
    "ID": 158,
    "Type": 1,
    "FirstName": "Ali",
    "MiddleName": "",
    "LastName": "Carter",
    "TeamName": "",
    "TeamNumber": 0,
    "TeamSeason": 0,
    "ShortName": "A Carter",
    "Nationality": "England",
    "Sex": "M",
    "BioPage": "",
    "Born": "1979-07-25",
    "Twitter": "TheCaptain147",
    "SurnameFirst": false,
    "License": "",
    "Club": "",
    "URL": "",
    "Photo": "https://snooker.org/img/players/carter.png",
    "PhotoSource": "",
    "FirstSeasonAsPro": 1996,
    "LastSeasonAsPro": 0,
    "Info": "",
    "NumRankingTitles": 6,
    "NumMaximums": 3,
    "Died": ""
  },
  {
    "ID": 163,
    "Type": 1,
    "FirstName": "Farakh",
    "MiddleName": "",
    "LastName": "Ajaib",
    "TeamName": "",
    "TeamNumber": 0,
    "TeamSeason": 0,
    "ShortName": "",
    "Nationality": "Pakistan",
    "Sex": "M",
    "BioPage": "",
    "Born": "1991-02-03",
    "Twitter": "AjaibFarakh",
    "SurnameFirst": false,
    "License": "",
    "Club": "",
    "URL": "",
    "Photo": "",
    "PhotoSource": "",
    "FirstSeasonAsPro": 2020,
    "LastSeasonAsPro": 0,
    "Info": "Represented England before 2020/2021",
    "NumRankingTitles": 0,
    "NumMaximums": 0,
    "Died": ""
  },
  {
    "ID": 168,
    "Type": 1,
    "FirstName": "Joe",
    "MiddleName": "",
    "LastName": "Perry",
    "TeamName": "",
    "TeamNumber": 0,
    "TeamSeason": 0,
    "ShortName": "",
    "Nationality": "England",
    "Sex": "M",
    "BioPage": "",
    "Born": "1974-08-13",
    "Twitter": "joegentlemanjoe",
    "SurnameFirst": false,
    "License": "",
    "Club": "",
    "URL": "",
    "Photo": "https://snooker.org/img/players/Perry.png",
    "PhotoSource": "",
    "FirstSeasonAsPro": 1992,
    "LastSeasonAsPro": 0,
    "Info": "",
    "NumRankingTitles": 2,
    "NumMaximums": 0,
    "Died": ""
  },
  {
    "ID": 170,
    "Type": 1,
    "FirstName": "Ken",
    "MiddleName": "",
    "LastName": "Doherty",
    "TeamName": "",
    "TeamNumber": 0,
    "TeamSeason": 0,
    "ShortName": "K Doherty",
    "Nationality": "Ireland",
    "Sex": "M",
    "BioPage": "https://snooker.org/plr/bio/kdoherty.shtml",
    "Born": "1969-09-17",
    "Twitter": "kendoherty1997",
    "SurnameFirst": false,
    "License": "",
    "Club": "",
    "URL": "",
    "Photo": "https://snooker.org/img/players/Doherty.png",
    "PhotoSource": "",
    "FirstSeasonAsPro": 1990,
    "LastSeasonAsPro": 0,
    "Info": "",
    "NumRankingTitles": 6,
    "NumMaximums": 1,
    "Died": ""
  },
  {
    "ID": 202,
    "Type": 1,
    "FirstName": "Mark",
    "MiddleName": "",
    "LastName": "Allen",
    "TeamName": "",
    "TeamNumber": 0,
    "TeamSeason": 0,
    "ShortName": "M Allen",
    "Nationality": "Northern Ireland",
    "Sex": "M",
    "BioPage": "",
    "Born": "1986-02-22",
    "Twitter": "pistol147",
    "SurnameFirst": false,
    "License": "",
    "Club": "",
    "URL": "",
    "Photo": "https://snooker.org/img/players/MarkAllen.png",
    "PhotoSource": "",
    "FirstSeasonAsPro": 2005,
    "LastSeasonAsPro": 0,
    "Info": "",
    "NumRankingTitles": 11,
    "NumMaximums": 4,
    "Died": ""
  },
  {
    "ID": 208,
    "Type": 1,
    "FirstName": "Noppon",
    "MiddleName": "",
    "LastName": "Saengkham",
    "TeamName": "",
    "TeamNumber": 0,
    "TeamSeason": 0,
    "ShortName": "",
    "Nationality": "Thailand",
    "Sex": "M",
    "BioPage": "",
    "Born": "1992-07-15",
    "Twitter": "",
    "SurnameFirst": false,
    "License": "",
    "Club": "",
    "URL": "",
    "Photo": "",
    "PhotoSource": "",
    "FirstSeasonAsPro": 2010,
    "LastSeasonAsPro": 0,
    "Info": "",
    "NumRankingTitles": 0,
    "NumMaximums": 3,
    "Died": ""
  },
  {
    "ID": 217,
    "Type": 1,
    "FirstName": "Thepchaiya",
    "MiddleName": "",
    "LastName": "Un-Nooh",
    "TeamName": "",
    "TeamNumber": 0,
    "TeamSeason": 0,
    "ShortName": "",
    "Nationality": "Thailand",
    "Sex": "M",
    "BioPage": "",
    "Born": "1985-04-18",
    "Twitter": "F1Un_Nooh",
    "SurnameFirst": false,
    "License": "",
    "Club": "",
    "URL": "",
    "Photo": "https://snooker.org/img/players/Un-Nooh.png",
    "PhotoSource": "",
    "FirstSeasonAsPro": 2009,
    "LastSeasonAsPro": 0,
    "Info": "",
    "NumRankingTitles": 1,
    "NumMaximums": 4,
    "Died": ""
  },
  {
    "ID": 218,
    "Type": 1,
    "FirstName": "Pengfei",
    "MiddleName": "",
    "LastName": "Tian",
    "TeamName": "",
    "TeamNumber": 0,
    "TeamSeason": 0,
    "ShortName": "Tian Pengfei",
    "Nationality": "China",
    "Sex": "M",
    "BioPage": "",
    "Born": "1987-08-16",
    "Twitter": "",
    "SurnameFirst": true,
    "License": "",
    "Club": "",
    "URL": "",
    "Photo": "https://snooker.org/img/players/Pengfei.png",
    "PhotoSource": "",
    "FirstSeasonAsPro": 2006,
    "LastSeasonAsPro": 0,
    "Info": "",
    "NumRankingTitles": 0,
    "NumMaximums": 0,
    "Died": ""
  },
  {
    "ID": 224,
    "Type": 1,
    "FirstName": "Junhui",
    "MiddleName": "",
    "LastName": "Ding",
    "TeamName": "",
    "TeamNumber": 0,
    "TeamSeason": 0,
    "ShortName": "Ding Junhui",
    "Nationality": "China",
    "Sex": "M",
    "BioPage": "",
    "Born": "1987-04-01",
    "Twitter": "",
    "SurnameFirst": true,
    "License": "",
    "Club": "",
    "URL": "",
    "Photo": "https://snooker.org/img/players/Dingjunhui.jpg",
    "PhotoSource": "",
    "FirstSeasonAsPro": 2003,
    "LastSeasonAsPro": 0,
    "Info": "",
    "NumRankingTitles": 15,
    "NumMaximums": 7,
    "Died": ""
  },
  {
    "ID": 237,
    "Type": 1,
    "FirstName": "John",
    "MiddleName": "",
    "LastName": "Higgins",
    "TeamName": "",
    "TeamNumber": 0,
    "TeamSeason": 0,
    "ShortName": "J Higgins",
    "Nationality": "Scotland",
    "Sex": "M",
    "BioPage": "https://snooker.org/plr/bio/jhiggins.shtml",
    "Born": "1975-05-18",
    "Twitter": "",
    "SurnameFirst": false,
    "License": "",
    "Club": "",
    "URL": "",
    "Photo": "https://snooker.org/img/players/jhiggins.jpg",
    "PhotoSource": "",
    "FirstSeasonAsPro": 1992,
    "LastSeasonAsPro": 0,
    "Info": "",
    "NumRankingTitles": 31,
    "NumMaximums": 13,
    "Died": ""
  },
  {
    "ID": 239,
    "Type": 1,
    "FirstName": "Alexander",
    "MiddleName": "",
    "LastName": "Ursenbacher",
    "TeamName": "",
    "TeamNumber": 0,
    "TeamSeason": 0,
    "ShortName": "",
    "Nationality": "Switzerland",
    "Sex": "M",
    "BioPage": "",
    "Born": "1996-04-26",
    "Twitter": "SwissNR1",
    "SurnameFirst": false,
    "License": "",
    "Club": "",
    "URL": "",
    "Photo": "",
    "PhotoSource": "",
    "FirstSeasonAsPro": 2013,
    "LastSeasonAsPro": 0,
    "Info": "",
    "NumRankingTitles": 0,
    "NumMaximums": 0,
    "Died": ""
  },
  {
    "ID": 418,
    "Type": 1,
    "FirstName": "Mohammed",
    "MiddleName": "",
    "LastName": "Shehab",
    "TeamName": "",
    "TeamNumber": 0,
    "TeamSeason": 0,
    "ShortName": "",
    "Nationality": "United Arab Emirates",
    "Sex": "M",
    "BioPage": "",
    "Born": "1976-12-11",
    "Twitter": "MohammedMShehab",
    "SurnameFirst": false,
    "License": "",
    "Club": "",
    "URL": "",
    "Photo": "",
    "PhotoSource": "",
    "FirstSeasonAsPro": 1996,
    "LastSeasonAsPro": 0,
    "Info": "",
    "NumRankingTitles": 0,
    "NumMaximums": 0,
    "Died": ""
  },
  {
    "ID": 448,
    "Type": 1,
    "FirstName": "Duane",
    "MiddleName": "",
    "LastName": "Jones",
    "TeamName": "",
    "TeamNumber": 0,
    "TeamSeason": 0,
    "ShortName": "D Jones",
    "Nationality": "Wales",
    "Sex": "M",
    "BioPage": "",
    "Born": "1993-04-30",
    "Twitter": "",
    "SurnameFirst": false,
    "License": "",
    "Club": "",
    "URL": "",
    "Photo": "",
    "PhotoSource": "",
    "FirstSeasonAsPro": 2015,
    "LastSeasonAsPro": 0,
    "Info": "",
    "NumRankingTitles": 0,
    "NumMaximums": 0,
    "Died": ""
  },
  {
    "ID": 507,
    "Type": 1,
    "FirstName": "Yupeng",
    "MiddleName": "",
    "LastName": "Cao",
    "TeamName": "",
    "TeamNumber": 0,
    "TeamSeason": 0,
    "ShortName": "Cao Yupeng",
    "Nationality": "China",
    "Sex": "M",
    "BioPage": "",
    "Born": "1990-10-27",
    "Twitter": "ECaoyupeng",
    "SurnameFirst": true,
    "License": "",
    "Club": "",
    "URL": "",
    "Photo": "https://snooker.org/img/players/Yupeng.png",
    "PhotoSource": "",
    "FirstSeasonAsPro": 2011,
    "LastSeasonAsPro": 0,
    "Info": "",
    "NumRankingTitles": 0,
    "NumMaximums": 1,
    "Died": ""
  },
  {
    "ID": 546,
    "Type": 1,
    "FirstName": "Gary",
    "MiddleName": "",
    "LastName": "Wilson",
    "TeamName": "",
    "TeamNumber": 0,
    "TeamSeason": 0,
    "ShortName": "G Wilson",
    "Nationality": "England",
    "Sex": "M",
    "BioPage": "",
    "Born": "1985-08-11",
    "Twitter": "Gary_Wilson11",
    "SurnameFirst": false,
    "License": "",
    "Club": "",
    "URL": "",
    "Photo": "https://snooker.org/img/players/Gary Wilson.png",
    "PhotoSource": "",
    "FirstSeasonAsPro": 2004,
    "LastSeasonAsPro": 0,
    "Info": "",
    "NumRankingTitles": 3,
    "NumMaximums": 5,
    "Died": ""
  },
  {
    "ID": 592,
    "Type": 1,
    "FirstName": "Oliver",
    "MiddleName": "",
    "LastName": "Lines",
    "TeamName": "",
    "TeamNumber": 0,
    "TeamSeason": 0,
    "ShortName": "O Lines",
    "Nationality": "England",
    "Sex": "M",
    "BioPage": "",
    "Born": "1995-06-16",
    "Twitter": "OliverLines",
    "SurnameFirst": false,
    "License": "",
    "Club": "",
    "URL": "",
    "Photo": "https://snooker.org/img/players/OLines.png",
    "PhotoSource": "",
    "FirstSeasonAsPro": 2014,
    "LastSeasonAsPro": 0,
    "Info": "",
    "NumRankingTitles": 0,
    "NumMaximums": 0,
    "Died": ""
  },
  {
    "ID": 593,
    "Type": 1,
    "FirstName": "Hammad",
    "MiddleName": "",
    "LastName": "Miah",
    "TeamName": "",
    "TeamNumber": 0,
    "TeamSeason": 0,
    "ShortName": "Hammad Miah",
    "Nationality": "England",
    "Sex": "M",
    "BioPage": "",
    "Born": "1993-07-06",
    "Twitter": "HammadMiah147",
    "SurnameFirst": false,
    "License": "",
    "Club": "",
    "URL": "",
    "Photo": "",
    "PhotoSource": "",
    "FirstSeasonAsPro": 2013,
    "LastSeasonAsPro": 0,
    "Info": "",
    "NumRankingTitles": 0,
    "NumMaximums": 0,
    "Died": ""
  },
  {
    "ID": 608,
    "Type": 1,
    "FirstName": "Elliot",
    "MiddleName": "",
    "LastName": "Slessor",
    "TeamName": "",
    "TeamNumber": 0,
    "TeamSeason": 0,
    "ShortName": "",
    "Nationality": "England",
    "Sex": "M",
    "BioPage": "",
    "Born": "1994-08-04",
    "Twitter": "sless147",
    "SurnameFirst": false,
    "License": "",
    "Club": "",
    "URL": "",
    "Photo": "",
    "PhotoSource": "",
    "FirstSeasonAsPro": 2013,
    "LastSeasonAsPro": 0,
    "Info": "",
    "NumRankingTitles": 0,
    "NumMaximums": 0,
    "Died": ""
  },
  {
    "ID": 621,
    "Type": 1,
    "FirstName": "Sanderson",
    "MiddleName": "",
    "LastName": "Lam",
    "TeamName": "",
    "TeamNumber": 0,
    "TeamSeason": 0,
    "ShortName": "S Lam",
    "Nationality": "England",
    "Sex": "M",
    "BioPage": "",
    "Born": "1994-01-28",
    "Twitter": "sandi147",
    "SurnameFirst": false,
    "License": "",
    "Club": "",
    "URL": "facebook.com/sandi147",
    "Photo": "",
    "PhotoSource": "",
    "FirstSeasonAsPro": 2015,
    "LastSeasonAsPro": 0,
    "Info": "",
    "NumRankingTitles": 0,
    "NumMaximums": 0,
    "Died": ""
  },
  {
    "ID": 666,
    "Type": 1,
    "FirstName": "Hossein",
    "MiddleName": "",
    "LastName": "Vafaei",
    "TeamName": "",
    "TeamNumber": 0,
    "TeamSeason": 0,
    "ShortName": "",
    "Nationality": "Iran",
    "Sex": "M",
    "BioPage": "",
    "Born": "1994-10-15",
    "Twitter": "hvafaei147",
    "SurnameFirst": false,
    "License": "",
    "Club": "",
    "URL": "",
    "Photo": "https://snooker.org/img/players/Hossein.png",
    "PhotoSource": "",
    "FirstSeasonAsPro": 2012,
    "LastSeasonAsPro": 0,
    "Info": "",
    "NumRankingTitles": 1,
    "NumMaximums": 1,
    "Died": ""
  },
  {
    "ID": 724,
    "Type": 1,
    "FirstName": "Ashley",
    "MiddleName": "",
    "LastName": "Carty",
    "TeamName": "",
    "TeamNumber": 0,
    "TeamSeason": 0,
    "ShortName": "",
    "Nationality": "England",
    "Sex": "M",
    "BioPage": "",
    "Born": "1995-07-17",
    "Twitter": "ashcarty147",
    "SurnameFirst": false,
    "License": "",
    "Club": "",
    "URL": "",
    "Photo": "https://snooker.org/img/players/Carty.png",
    "PhotoSource": "",
    "FirstSeasonAsPro": 2018,
    "LastSeasonAsPro": 0,
    "Info": "",
    "NumRankingTitles": 0,
    "NumMaximums": 0,
    "Died": ""
  },
  {
    "ID": 894,
    "Type": 1,
    "FirstName": "Scott",
    "MiddleName": "",
    "LastName": "Donaldson",
    "TeamName": "",
    "TeamNumber": 0,
    "TeamSeason": 0,
    "ShortName": "",
    "Nationality": "Scotland",
    "Sex": "M",
    "BioPage": "",
    "Born": "1994-03-19",
    "Twitter": "",
    "SurnameFirst": false,
    "License": "",
    "Club": "",
    "URL": "",
    "Photo": "https://snooker.org/img/players/Donaldson.png",
    "PhotoSource": "",
    "FirstSeasonAsPro": 2012,
    "LastSeasonAsPro": 0,
    "Info": "",
    "NumRankingTitles": 0,
    "NumMaximums": 0,
    "Died": ""
  },
  {
    "ID": 898,
    "Type": 1,
    "FirstName": "Ross",
    "MiddleName": "",
    "LastName": "Muir",
    "TeamName": "",
    "TeamNumber": 0,
    "TeamSeason": 0,
    "ShortName": "",
    "Nationality": "Scotland",
    "Sex": "M",
    "BioPage": "",
    "Born": "1995-10-06",
    "Twitter": "rossmuir147",
    "SurnameFirst": false,
    "License": "",
    "Club": "",
    "URL": "https://www.facebook.com/RossMuirSnooker/",
    "Photo": "https://snooker.org/img/players/Muir.png",
    "PhotoSource": "",
    "FirstSeasonAsPro": 2013,
    "LastSeasonAsPro": 0,
    "Info": "",
    "NumRankingTitles": 0,
    "NumMaximums": 1,
    "Died": ""
  },
  {
    "ID": 905,
    "Type": 1,
    "FirstName": "Haotian",
    "MiddleName": "",
    "LastName": "Lyu",
    "TeamName": "",
    "TeamNumber": 0,
    "TeamSeason": 0,
    "ShortName": "Lyu Haotian",
    "Nationality": "China",
    "Sex": "M",
    "BioPage": "",
    "Born": "1997-11-29",
    "Twitter": "",
    "SurnameFirst": true,
    "License": "",
    "Club": "",
    "URL": "",
    "Photo": "",
    "PhotoSource": "",
    "FirstSeasonAsPro": 2013,
    "LastSeasonAsPro": 0,
    "Info": "",
    "NumRankingTitles": 0,
    "NumMaximums": 0,
    "Died": ""
  },
  {
    "ID": 906,
    "Type": 1,
    "FirstName": "Yuelong",
    "MiddleName": "",
    "LastName": "Zhou",
    "TeamName": "",
    "TeamNumber": 0,
    "TeamSeason": 0,
    "ShortName": "Zhou Yuelong",
    "Nationality": "China",
    "Sex": "M",
    "BioPage": "",
    "Born": "1998-01-24",
    "Twitter": "yuelong_zhou",
    "SurnameFirst": true,
    "License": "",
    "Club": "",
    "URL": "",
    "Photo": "https://snooker.org/img/players/Yuelong.png",
    "PhotoSource": "",
    "FirstSeasonAsPro": 2014,
    "LastSeasonAsPro": 0,
    "Info": "",
    "NumRankingTitles": 0,
    "NumMaximums": 2,
    "Died": ""
  },
  {
    "ID": 954,
    "Type": 1,
    "FirstName": "Yuchen",
    "MiddleName": "",
    "LastName": "Wang",
    "TeamName": "",
    "TeamNumber": 0,
    "TeamSeason": 0,
    "ShortName": "Wang Yuchen",
    "Nationality": "Hong Kong",
    "Sex": "M",
    "BioPage": "",
    "Born": "1997-08-05",
    "Twitter": "",
    "SurnameFirst": true,
    "License": "",
    "Club": "",
    "URL": "",
    "Photo": "",
    "PhotoSource": "",
    "FirstSeasonAsPro": 2016,
    "LastSeasonAsPro": 0,
    "Info": "previously represented China",
    "NumRankingTitles": 0,
    "NumMaximums": 0,
    "Died": ""
  },
  {
    "ID": 998,
    "Type": 1,
    "FirstName": "David",
    "MiddleName": "",
    "LastName": "Lilley",
    "TeamName": "",
    "TeamNumber": 0,
    "TeamSeason": 0,
    "ShortName": "D Lilley",
    "Nationality": "England",
    "Sex": "M",
    "BioPage": "",
    "Born": "1975-10-19",
    "Twitter": "dlilley2011",
    "SurnameFirst": false,
    "License": "",
    "Club": "",
    "URL": "",
    "Photo": "",
    "PhotoSource": "",
    "FirstSeasonAsPro": 2019,
    "LastSeasonAsPro": 0,
    "Info": "",
    "NumRankingTitles": 0,
    "NumMaximums": 0,
    "Died": ""
  },
  {
    "ID": 1038,
    "Type": 1,
    "FirstName": "Joe",
    "MiddleName": "",
    "LastName": "O'Connor",
    "TeamName": "",
    "TeamNumber": 0,
    "TeamSeason": 0,
    "ShortName": "J O'Connor",
    "Nationality": "England",
    "Sex": "M",
    "BioPage": "",
    "Born": "1995-11-08",
    "Twitter": "JoeOc147",
    "SurnameFirst": false,
    "License": "",
    "Club": "",
    "URL": "",
    "Photo": "",
    "PhotoSource": "",
    "FirstSeasonAsPro": 2018,
    "LastSeasonAsPro": 0,
    "Info": "",
    "NumRankingTitles": 0,
    "NumMaximums": 1,
    "Died": ""
  },
  {
    "ID": 1044,
    "Type": 1,
    "FirstName": "Chris",
    "MiddleName": "",
    "LastName": "Wakelin",
    "TeamName": "",
    "TeamNumber": 0,
    "TeamSeason": 0,
    "ShortName": "C Wakelin",
    "Nationality": "England",
    "Sex": "M",
    "BioPage": "",
    "Born": "1992-03-16",
    "Twitter": "chris147ace",
    "SurnameFirst": false,
    "License": "",
    "Club": "",
    "URL": "",
    "Photo": "https://snooker.org/img/players/Wakelin.png",
    "PhotoSource": "",
    "FirstSeasonAsPro": 2013,
    "LastSeasonAsPro": 0,
    "Info": "",
    "NumRankingTitles": 1,
    "NumMaximums": 0,
    "Died": ""
  },
  {
    "ID": 1045,
    "Type": 1,
    "FirstName": "Louis",
    "MiddleName": "",
    "LastName": "Heathcote",
    "TeamName": "",
    "TeamNumber": 0,
    "TeamSeason": 0,
    "ShortName": "",
    "Nationality": "England",
    "Sex": "M",
    "BioPage": "",
    "Born": "1997-07-03",
    "Twitter": "",
    "SurnameFirst": false,
    "License": "",
    "Club": "",
    "URL": "",
    "Photo": "",
    "PhotoSource": "",
    "FirstSeasonAsPro": 2019,
    "LastSeasonAsPro": 0,
    "Info": "",
    "NumRankingTitles": 0,
    "NumMaximums": 0,
    "Died": ""
  },
  {
    "ID": 1108,
    "Type": 1,
    "FirstName": "Sijun",
    "MiddleName": "",
    "LastName": "Yuan",
    "TeamName": "",
    "TeamNumber": 0,
    "TeamSeason": 0,
    "ShortName": "Yuan Sijun",
    "Nationality": "China",
    "Sex": "M",
    "BioPage": "",
    "Born": "2000-05-29",
    "Twitter": "",
    "SurnameFirst": true,
    "License": "",
    "Club": "",
    "URL": "",
    "Photo": "",
    "PhotoSource": "",
    "FirstSeasonAsPro": 2017,
    "LastSeasonAsPro": 0,
    "Info": "",
    "NumRankingTitles": 0,
    "NumMaximums": 0,
    "Died": ""
  },
  {
    "ID": 1149,
    "Type": 1,
    "FirstName": "Jiahao",
    "MiddleName": "",
    "LastName": "Huang",
    "TeamName": "",
    "TeamNumber": 0,
    "TeamSeason": 0,
    "ShortName": "Huang Jiahao",
    "Nationality": "China",
    "Sex": "M",
    "BioPage": "",
    "Born": "1995-08-17",
    "Twitter": "",
    "SurnameFirst": true,
    "License": "",
    "Club": "",
    "URL": "",
    "Photo": "",
    "PhotoSource": "",
    "FirstSeasonAsPro": 2024,
    "LastSeasonAsPro": 0,
    "Info": "",
    "NumRankingTitles": 0,
    "NumMaximums": 0,
    "Died": ""
  },
  {
    "ID": 1186,
    "Type": 1,
    "FirstName": "Chris",
    "MiddleName": "",
    "LastName": "Totten",
    "TeamName": "",
    "TeamNumber": 0,
    "TeamSeason": 0,
    "ShortName": "",
    "Nationality": "Scotland",
    "Sex": "M",
    "BioPage": "",
    "Born": "1998-12-05",
    "Twitter": "chris_147t",
    "SurnameFirst": false,
    "License": "",
    "Club": "",
    "URL": "",
    "Photo": "",
    "PhotoSource": "",
    "FirstSeasonAsPro": 2017,
    "LastSeasonAsPro": 0,
    "Info": "",
    "NumRankingTitles": 0,
    "NumMaximums": 0,
    "Died": ""
  },
  {
    "ID": 1257,
    "Type": 1,
    "FirstName": "Junxu",
    "MiddleName": "",
    "LastName": "Pang",
    "TeamName": "",
    "TeamNumber": 0,
    "TeamSeason": 0,
    "ShortName": "Pang Junxu",
    "Nationality": "China",
    "Sex": "M",
    "BioPage": "",
    "Born": "2000-02-15",
    "Twitter": "",
    "SurnameFirst": true,
    "License": "",
    "Club": "",
    "URL": "",
    "Photo": "",
    "PhotoSource": "",
    "FirstSeasonAsPro": 2020,
    "LastSeasonAsPro": 0,
    "Info": "",
    "NumRankingTitles": 0,
    "NumMaximums": 0,
    "Died": ""
  },
  {
    "ID": 1261,
    "Type": 1,
    "FirstName": "Zehuang",
    "MiddleName": "",
    "LastName": "Long",
    "TeamName": "",
    "TeamNumber": 0,
    "TeamSeason": 0,
    "ShortName": "Long Zehuang",
    "Nationality": "China",
    "Sex": "M",
    "BioPage": "",
    "Born": "1996-12-28",
    "Twitter": "",
    "SurnameFirst": true,
    "License": "",
    "Club": "",
    "URL": "",
    "Photo": "",
    "PhotoSource": "",
    "FirstSeasonAsPro": 2023,
    "LastSeasonAsPro": 0,
    "Info": "",
    "NumRankingTitles": 0,
    "NumMaximums": 0,
    "Died": ""
  },
  {
    "ID": 1350,
    "Type": 1,
    "FirstName": "Amir",
    "MiddleName": "",
    "LastName": "Sarkhosh",
    "TeamName": "",
    "TeamNumber": 0,
    "TeamSeason": 0,
    "ShortName": "",
    "Nationality": "Iran",
    "Sex": "M",
    "BioPage": "",
    "Born": "1991-05-30",
    "Twitter": "",
    "SurnameFirst": false,
    "License": "",
    "Club": "",
    "URL": "",
    "Photo": "",
    "PhotoSource": "",
    "FirstSeasonAsPro": 2024,
    "LastSeasonAsPro": 0,
    "Info": "",
    "NumRankingTitles": 0,
    "NumMaximums": 0,
    "Died": ""
  },
  {
    "ID": 1383,
    "Type": 1,
    "FirstName": "Guoqiang",
    "MiddleName": "",
    "LastName": "He",
    "TeamName": "",
    "TeamNumber": 0,
    "TeamSeason": 0,
    "ShortName": "He Guoqiang",
    "Nationality": "China",
    "Sex": "M",
    "BioPage": "",
    "Born": "2000-08-05",
    "Twitter": "",
    "SurnameFirst": true,
    "License": "",
    "Club": "",
    "URL": "",
    "Photo": "",
    "PhotoSource": "",
    "FirstSeasonAsPro": 2023,
    "LastSeasonAsPro": 0,
    "Info": "made a 147 at 2018 IBSF U-21 World Championship",
    "NumRankingTitles": 0,
    "NumMaximums": 0,
    "Died": ""
  },
  {
    "ID": 1407,
    "Type": 1,
    "FirstName": "Si",
    "MiddleName": "",
    "LastName": "Xu",
    "TeamName": "",
    "TeamNumber": 0,
    "TeamSeason": 0,
    "ShortName": "Xu Si",
    "Nationality": "China",
    "Sex": "M",
    "BioPage": "",
    "Born": "1998-01-24",
    "Twitter": "",
    "SurnameFirst": true,
    "License": "",
    "Club": "",
    "URL": "",
    "Photo": "",
    "PhotoSource": "",
    "FirstSeasonAsPro": 2017,
    "LastSeasonAsPro": 0,
    "Info": "",
    "NumRankingTitles": 0,
    "NumMaximums": 2,
    "Died": ""
  },
  {
    "ID": 1417,
    "Type": 1,
    "FirstName": "Zhengyi",
    "MiddleName": "",
    "LastName": "Fan",
    "TeamName": "",
    "TeamNumber": 0,
    "TeamSeason": 0,
    "ShortName": "Fan Zhengyi",
    "Nationality": "China",
    "Sex": "M",
    "BioPage": "",
    "Born": "2001-01-27",
    "Twitter": "",
    "SurnameFirst": true,
    "License": "",
    "Club": "",
    "URL": "",
    "Photo": "",
    "PhotoSource": "",
    "FirstSeasonAsPro": 2018,
    "LastSeasonAsPro": 0,
    "Info": "",
    "NumRankingTitles": 1,
    "NumMaximums": 1,
    "Died": ""
  },
  {
    "ID": 1465,
    "Type": 1,
    "FirstName": "Antoni",
    "MiddleName": "",
    "LastName": "Kowalski",
    "TeamName": "",
    "TeamNumber": 0,
    "TeamSeason": 0,
    "ShortName": "A Kowalski",
    "Nationality": "Poland",
    "Sex": "M",
    "BioPage": "",
    "Born": "2004-02-09",
    "Twitter": "",
    "SurnameFirst": false,
    "License": "",
    "Club": "",
    "URL": "",
    "Photo": "",
    "PhotoSource": "",
    "FirstSeasonAsPro": 2024,
    "LastSeasonAsPro": 0,
    "Info": "",
    "NumRankingTitles": 0,
    "NumMaximums": 0,
    "Died": ""
  },
  {
    "ID": 1509,
    "Type": 1,
    "FirstName": "Rory",
    "MiddleName": "",
    "LastName": "Thor",
    "TeamName": "",
    "TeamNumber": 0,
    "TeamSeason": 0,
    "ShortName": "",
    "Nationality": "Malaysia",
    "Sex": "M",
    "BioPage": "",
    "Born": "1988-03-24",
    "Twitter": "",
    "SurnameFirst": false,
    "License": "",
    "Club": "",
    "URL": "",
    "Photo": "https://snooker.org/img/players/Leong.png",
    "PhotoSource": "",
    "FirstSeasonAsPro": 2014,
    "LastSeasonAsPro": 0,
    "Info": "also known as Thor Chuan Leong",
    "NumRankingTitles": 0,
    "NumMaximums": 0,
    "Died": ""
  },
  {
    "ID": 1763,
    "Type": 1,
    "FirstName": "Sunny",
    "MiddleName": "",
    "LastName": "Akani",
    "TeamName": "",
    "TeamNumber": 0,
    "TeamSeason": 0,
    "ShortName": "Sunny Akani",
    "Nationality": "Thailand",
    "Sex": "M",
    "BioPage": "",
    "Born": "1995-09-10",
    "Twitter": "",
    "SurnameFirst": false,
    "License": "",
    "Club": "",
    "URL": "",
    "Photo": "",
    "PhotoSource": "",
    "FirstSeasonAsPro": 2015,
    "LastSeasonAsPro": 0,
    "Info": "also known as Akani Songsermsawad",
    "NumRankingTitles": 0,
    "NumMaximums": 0,
    "Died": ""
  },
  {
    "ID": 1764,
    "Type": 1,
    "FirstName": "Hatem",
    "MiddleName": "",
    "LastName": "Yassen",
    "TeamName": "",
    "TeamNumber": 0,
    "TeamSeason": 0,
    "ShortName": "",
    "Nationality": "Egypt",
    "Sex": "M",
    "BioPage": "",
    "Born": "1986-08-21",
    "Twitter": "",
    "SurnameFirst": false,
    "License": "",
    "Club": "",
    "URL": "",
    "Photo": "",
    "PhotoSource": "",
    "FirstSeasonAsPro": 2015,
    "LastSeasonAsPro": 0,
    "Info": "Won the 2024 African Championship so will be nominated for a Main Tour card",
    "NumRankingTitles": 0,
    "NumMaximums": 0,
    "Died": ""
  },
  {
    "ID": 1844,
    "Type": 1,
    "FirstName": "Mostafa",
    "MiddleName": "",
    "LastName": "Dorgham",
    "TeamName": "",
    "TeamNumber": 0,
    "TeamSeason": 0,
    "ShortName": "",
    "Nationality": "Egypt",
    "Sex": "M",
    "BioPage": "",
    "Born": "1996-01-10",
    "Twitter": "",
    "SurnameFirst": false,
    "License": "",
    "Club": "",
    "URL": "https://www.facebook.com/mostafa.shawky.921",
    "Photo": "",
    "PhotoSource": "",
    "FirstSeasonAsPro": 2023,
    "LastSeasonAsPro": 0,
    "Info": "2023 African Snooker Champion",
    "NumRankingTitles": 0,
    "NumMaximums": 0,
    "Died": ""
  },
  {
    "ID": 1893,
    "Type": 1,
    "FirstName": "Ka Wai",
    "MiddleName": "",
    "LastName": "Cheung",
    "TeamName": "",
    "TeamNumber": 0,
    "TeamSeason": 0,
    "ShortName": "Cheung Ka Wai",
    "Nationality": "Hong Kong",
    "Sex": "M",
    "BioPage": "",
    "Born": "1999-02-17",
    "Twitter": "",
    "SurnameFirst": true,
    "License": "",
    "Club": "",
    "URL": "",
    "Photo": "",
    "PhotoSource": "",
    "FirstSeasonAsPro": 2024,
    "LastSeasonAsPro": 0,
    "Info": "",
    "NumRankingTitles": 0,
    "NumMaximums": 0,
    "Died": ""
  },
  {
    "ID": 1923,
    "Type": 1,
    "FirstName": "Ben",
    "MiddleName": "",
    "LastName": "Mertens",
    "TeamName": "",
    "TeamNumber": 0,
    "TeamSeason": 0,
    "ShortName": "",
    "Nationality": "Belgium",
    "Sex": "M",
    "BioPage": "",
    "Born": "2004-10-13",
    "Twitter": "benmertens2004",
    "SurnameFirst": false,
    "License": "",
    "Club": "",
    "URL": "",
    "Photo": "",
    "PhotoSource": "",
    "FirstSeasonAsPro": 2022,
    "LastSeasonAsPro": 0,
    "Info": "",
    "NumRankingTitles": 0,
    "NumMaximums": 0,
    "Died": ""
  },
  {
    "ID": 1982,
    "Type": 1,
    "FirstName": "Jiahui",
    "MiddleName": "",
    "LastName": "Si",
    "TeamName": "",
    "TeamNumber": 0,
    "TeamSeason": 0,
    "ShortName": "Si Jiahui",
    "Nationality": "China",
    "Sex": "M",
    "BioPage": "",
    "Born": "2002-07-11",
    "Twitter": "",
    "SurnameFirst": true,
    "License": "",
    "Club": "",
    "URL": "",
    "Photo": "",
    "PhotoSource": "",
    "FirstSeasonAsPro": 2019,
    "LastSeasonAsPro": 0,
    "Info": "",
    "NumRankingTitles": 0,
    "NumMaximums": 1,
    "Died": ""
  },
  {
    "ID": 1991,
    "Type": 1,
    "FirstName": "Manasawin",
    "MiddleName": "",
    "LastName": "Phetmalaikul",
    "TeamName": "",
    "TeamNumber": 0,
    "TeamSeason": 0,
    "ShortName": "",
    "Nationality": "Thailand",
    "Sex": "M",
    "BioPage": "",
    "Born": "1999-05-19",
    "Twitter": "Manasawin_19",
    "SurnameFirst": false,
    "License": "",
    "Club": "",
    "URL": "",
    "Photo": "",
    "PhotoSource": "",
    "FirstSeasonAsPro": 2023,
    "LastSeasonAsPro": 0,
    "Info": "also eligible to represent England",
    "NumRankingTitles": 0,
    "NumMaximums": 0,
    "Died": ""
  },
  {
    "ID": 2061,
    "Type": 1,
    "FirstName": "Haydon",
    "MiddleName": "",
    "LastName": "Pinhey",
    "TeamName": "",
    "TeamNumber": 0,
    "TeamSeason": 0,
    "ShortName": "",
    "Nationality": "England",
    "Sex": "M",
    "BioPage": "",
    "Born": "1996-07-30",
    "Twitter": "",
    "SurnameFirst": false,
    "License": "",
    "Club": "",
    "URL": "",
    "Photo": "",
    "PhotoSource": "",
    "FirstSeasonAsPro": 2024,
    "LastSeasonAsPro": 0,
    "Info": "",
    "NumRankingTitles": 0,
    "NumMaximums": 0,
    "Died": ""
  },
  {
    "ID": 2066,
    "Type": 1,
    "FirstName": "Ishpreet",
    "MiddleName": "Singh",
    "LastName": "Chadha",
    "TeamName": "",
    "TeamNumber": 0,
    "TeamSeason": 0,
    "ShortName": "",
    "Nationality": "India",
    "Sex": "M",
    "BioPage": "",
    "Born": "1996-05-30",
    "Twitter": "Ishpreet147",
    "SurnameFirst": false,
    "License": "",
    "Club": "",
    "URL": "https://www.facebook.com/ishu.HuNtR/",
    "Photo": "",
    "PhotoSource": "",
    "FirstSeasonAsPro": 2023,
    "LastSeasonAsPro": 0,
    "Info": "Until 2021 Chadha played CS:GO and Valorant professionally, where he was known as HuntR",
    "NumRankingTitles": 0,
    "NumMaximums": 0,
    "Died": ""
  },
  {
    "ID": 2166,
    "Type": 1,
    "FirstName": "Jackson",
    "MiddleName": "",
    "LastName": "Page",
    "TeamName": "",
    "TeamNumber": 0,
    "TeamSeason": 0,
    "ShortName": "J Page",
    "Nationality": "Wales",
    "Sex": "M",
    "BioPage": "",
    "Born": "2001-08-08",
    "Twitter": "JacksonPage147",
    "SurnameFirst": false,
    "License": "",
    "Club": "",
    "URL": "",
    "Photo": "",
    "PhotoSource": "",
    "FirstSeasonAsPro": 2019,
    "LastSeasonAsPro": 0,
    "Info": "",
    "NumRankingTitles": 0,
    "NumMaximums": 0,
    "Died": ""
  },
  {
    "ID": 2346,
    "Type": 1,
    "FirstName": "Ahmed",
    "MiddleName": "Aly",
    "LastName": "Elsayed",
    "TeamName": "",
    "TeamNumber": 0,
    "TeamSeason": 0,
    "ShortName": "A Elsayed",
    "Nationality": "United States",
    "Sex": "M",
    "BioPage": "",
    "Born": "1979-12-14",
    "Twitter": "",
    "SurnameFirst": false,
    "License": "",
    "Club": "",
    "URL": "",
    "Photo": "",
    "PhotoSource": "",
    "FirstSeasonAsPro": 2023,
    "LastSeasonAsPro": 0,
    "Info": "",
    "NumRankingTitles": 0,
    "NumMaximums": 0,
    "Died": ""
  },
  {
    "ID": 2438,
    "Type": 1,
    "FirstName": "Liam",
    "MiddleName": "",
    "LastName": "Davies",
    "TeamName": "",
    "TeamNumber": 0,
    "TeamSeason": 0,
    "ShortName": "L J Davies",
    "Nationality": "Wales",
    "Sex": "M",
    "BioPage": "",
    "Born": "2006-06-28",
    "Twitter": "",
    "SurnameFirst": false,
    "License": "",
    "Club": "",
    "URL": "",
    "Photo": "",
    "PhotoSource": "",
    "FirstSeasonAsPro": 2024,
    "LastSeasonAsPro": 0,
    "Info": "His full name is Liam James Davies",
    "NumRankingTitles": 0,
    "NumMaximums": 0,
    "Died": ""
  },
  {
    "ID": 2439,
    "Type": 1,
    "FirstName": "Liam",
    "MiddleName": "",
    "LastName": "Graham",
    "TeamName": "",
    "TeamNumber": 0,
    "TeamSeason": 0,
    "ShortName": "L Graham",
    "Nationality": "Scotland",
    "Sex": "M",
    "BioPage": "",
    "Born": "2004-09-12",
    "Twitter": "",
    "SurnameFirst": false,
    "License": "",
    "Club": "",
    "URL": "",
    "Photo": "",
    "PhotoSource": "",
    "FirstSeasonAsPro": 2023,
    "LastSeasonAsPro": 0,
    "Info": "",
    "NumRankingTitles": 0,
    "NumMaximums": 0,
    "Died": ""
  },
  {
    "ID": 2469,
    "Type": 1,
    "FirstName": "Yize",
    "MiddleName": "",
    "LastName": "Wu",
    "TeamName": "",
    "TeamNumber": 0,
    "TeamSeason": 0,
    "ShortName": "Wu Yize",
    "Nationality": "China",
    "Sex": "M",
    "BioPage": "",
    "Born": "2003-10-14",
    "Twitter": "",
    "SurnameFirst": true,
    "License": "",
    "Club": "",
    "URL": "",
    "Photo": "",
    "PhotoSource": "",
    "FirstSeasonAsPro": 2021,
    "LastSeasonAsPro": 0,
    "Info": "",
    "NumRankingTitles": 0,
    "NumMaximums": 0,
    "Died": ""
  },
  {
    "ID": 2470,
    "Type": 1,
    "FirstName": "Aaron",
    "MiddleName": "",
    "LastName": "Hill",
    "TeamName": "",
    "TeamNumber": 0,
    "TeamSeason": 0,
    "ShortName": "A Hill",
    "Nationality": "Ireland",
    "Sex": "M",
    "BioPage": "",
    "Born": "2002-02-28",
    "Twitter": "AaronHill147",
    "SurnameFirst": false,
    "License": "",
    "Club": "",
    "URL": "",
    "Photo": "",
    "PhotoSource": "",
    "FirstSeasonAsPro": 2020,
    "LastSeasonAsPro": 0,
    "Info": "",
    "NumRankingTitles": 0,
    "NumMaximums": 0,
    "Died": ""
  },
  {
    "ID": 2497,
    "Type": 1,
    "FirstName": "Kreishh",
    "MiddleName": "",
    "LastName": "Gurbaxani",
    "TeamName": "",
    "TeamNumber": 0,
    "TeamSeason": 0,
    "ShortName": "",
    "Nationality": "India",
    "Sex": "M",
    "BioPage": "",
    "Born": "2002-08-23",
    "Twitter": "",
    "SurnameFirst": false,
    "License": "",
    "Club": "",
    "URL": "",
    "Photo": "https://snooker.org/img/players/Gurbaxani-1.JPG",
    "PhotoSource": "Marian",
    "FirstSeasonAsPro": 2024,
    "LastSeasonAsPro": 0,
    "Info": "",
    "NumRankingTitles": 0,
    "NumMaximums": 0,
    "Died": ""
  },
  {
    "ID": 2498,
    "Type": 1,
    "FirstName": "Peifan",
    "MiddleName": "",
    "LastName": "Lei",
    "TeamName": "",
    "TeamNumber": 0,
    "TeamSeason": 0,
    "ShortName": "Lei Peifan",
    "Nationality": "China",
    "Sex": "M",
    "BioPage": "",
    "Born": "2003-05-31",
    "Twitter": "",
    "SurnameFirst": true,
    "License": "",
    "Club": "",
    "URL": "",
    "Photo": "",
    "PhotoSource": "",
    "FirstSeasonAsPro": 2019,
    "LastSeasonAsPro": 0,
    "Info": "",
    "NumRankingTitles": 0,
    "NumMaximums": 0,
    "Died": ""
  },
  {
    "ID": 2499,
    "Type": 1,
    "FirstName": "Dean",
    "MiddleName": "",
    "LastName": "Young",
    "TeamName": "",
    "TeamNumber": 0,
    "TeamSeason": 0,
    "ShortName": "D Young",
    "Nationality": "Scotland",
    "Sex": "M",
    "BioPage": "",
    "Born": "2002-01-07",
    "Twitter": "",
    "SurnameFirst": false,
    "License": "",
    "Club": "",
    "URL": "",
    "Photo": "",
    "PhotoSource": "",
    "FirstSeasonAsPro": 2021,
    "LastSeasonAsPro": 0,
    "Info": "",
    "NumRankingTitles": 0,
    "NumMaximums": 0,
    "Died": ""
  },
  {
    "ID": 2507,
    "Type": 1,
    "FirstName": "Robbie",
    "MiddleName": "",
    "LastName": "McGuigan",
    "TeamName": "",
    "TeamNumber": 0,
    "TeamSeason": 0,
    "ShortName": "",
    "Nationality": "Northern Ireland",
    "Sex": "M",
    "BioPage": "",
    "Born": "2004-07-07",
    "Twitter": "Robbiemcg147",
    "SurnameFirst": false,
    "License": "",
    "Club": "",
    "URL": "",
    "Photo": "",
    "PhotoSource": "",
    "FirstSeasonAsPro": 2024,
    "LastSeasonAsPro": 0,
    "Info": "",
    "NumRankingTitles": 0,
    "NumMaximums": 0,
    "Died": ""
  },
  {
    "ID": 2608,
    "Type": 1,
    "FirstName": "Hailong",
    "MiddleName": "",
    "LastName": "Ma",
    "TeamName": "",
    "TeamNumber": 0,
    "TeamSeason": 0,
    "ShortName": "Ma Hailong",
    "Nationality": "China",
    "Sex": "M",
    "BioPage": "",
    "Born": "2003-09-04",
    "Twitter": "",
    "SurnameFirst": true,
    "License": "",
    "Club": "",
    "URL": "",
    "Photo": "",
    "PhotoSource": "",
    "FirstSeasonAsPro": 2023,
    "LastSeasonAsPro": 0,
    "Info": "",
    "NumRankingTitles": 0,
    "NumMaximums": 0,
    "Died": ""
  },
  {
    "ID": 2611,
    "Type": 1,
    "FirstName": "Hongyu",
    "MiddleName": "",
    "LastName": "Liu",
    "TeamName": "",
    "TeamNumber": 0,
    "TeamSeason": 0,
    "ShortName": "Liu Hongyu",
    "Nationality": "China",
    "Sex": "M",
    "BioPage": "",
    "Born": "2004-04-21",
    "Twitter": "",
    "SurnameFirst": true,
    "License": "",
    "Club": "",
    "URL": "",
    "Photo": "",
    "PhotoSource": "",
    "FirstSeasonAsPro": 2023,
    "LastSeasonAsPro": 0,
    "Info": "",
    "NumRankingTitles": 0,
    "NumMaximums": 0,
    "Died": ""
  },
  {
    "ID": 2630,
    "Type": 1,
    "FirstName": "Zihao",
    "MiddleName": "",
    "LastName": "Xing",
    "TeamName": "",
    "TeamNumber": 0,
    "TeamSeason": 0,
    "ShortName": "Xing Zihao",
    "Nationality": "China",
    "Sex": "M",
    "BioPage": "",
    "Born": "2004-11-06",
    "Twitter": "",
    "SurnameFirst": true,
    "License": "",
    "Club": "",
    "URL": "",
    "Photo": "",
    "PhotoSource": "",
    "FirstSeasonAsPro": 2023,
    "LastSeasonAsPro": 0,
    "Info": "",
    "NumRankingTitles": 0,
    "NumMaximums": 0,
    "Died": ""
  },
  {
    "ID": 2634,
    "Type": 1,
    "FirstName": "Chenzhi",
    "MiddleName": "",
    "LastName": "Gong",
    "TeamName": "",
    "TeamNumber": 0,
    "TeamSeason": 0,
    "ShortName": "Gong Chenzhi",
    "Nationality": "China",
    "Sex": "M",
    "BioPage": "",
    "Born": "2006-09-22",
    "Twitter": "",
    "SurnameFirst": true,
    "License": "",
    "Club": "",
    "URL": "",
    "Photo": "",
    "PhotoSource": "",
    "FirstSeasonAsPro": 2024,
    "LastSeasonAsPro": 0,
    "Info": "",
    "NumRankingTitles": 0,
    "NumMaximums": 0,
    "Died": ""
  },
  {
    "ID": 2640,
    "Type": 1,
    "FirstName": "Jun",
    "MiddleName": "",
    "LastName": "Jiang",
    "TeamName": "",
    "TeamNumber": 0,
    "TeamSeason": 0,
    "ShortName": "Jiang Jun",
    "Nationality": "China",
    "Sex": "M",
    "BioPage": "",
    "Born": "2005-08-28",
    "Twitter": "",
    "SurnameFirst": true,
    "License": "",
    "Club": "",
    "URL": "",
    "Photo": "",
    "PhotoSource": "",
    "FirstSeasonAsPro": 2023,
    "LastSeasonAsPro": 0,
    "Info": "",
    "NumRankingTitles": 0,
    "NumMaximums": 0,
    "Died": ""
  },
  {
    "ID": 2655,
    "Type": 1,
    "FirstName": "Bulcsu",
    "MiddleName": "",
    "LastName": "Revesz",
    "TeamName": "",
    "TeamNumber": 0,
    "TeamSeason": 0,
    "ShortName": "",
    "Nationality": "Hungary",
    "Sex": "M",
    "BioPage": "",
    "Born": "2007-01-01",
    "Twitter": "",
    "SurnameFirst": false,
    "License": "",
    "Club": "",
    "URL": "https://www.facebook.com/profile.php?id=100063582398193",
    "Photo": "",
    "PhotoSource": "",
    "FirstSeasonAsPro": 2024,
    "LastSeasonAsPro": 0,
    "Info": "",
    "NumRankingTitles": 0,
    "NumMaximums": 0,
    "Died": ""
  },
  {
    "ID": 2754,
    "Type": 1,
    "FirstName": "Julien",
    "MiddleName": "",
    "LastName": "Leclercq",
    "TeamName": "",
    "TeamNumber": 0,
    "TeamSeason": 0,
    "ShortName": "",
    "Nationality": "Belgium",
    "Sex": "M",
    "BioPage": "",
    "Born": "2003-02-03",
    "Twitter": "JulienL25401033",
    "SurnameFirst": false,
    "License": "",
    "Club": "",
    "URL": "",
    "Photo": "",
    "PhotoSource": "",
    "FirstSeasonAsPro": 2022,
    "LastSeasonAsPro": 0,
    "Info": "",
    "NumRankingTitles": 0,
    "NumMaximums": 0,
    "Died": ""
  },
  {
    "ID": 2758,
    "Type": 1,
    "FirstName": "Stan",
    "MiddleName": "",
    "LastName": "Moody",
    "TeamName": "",
    "TeamNumber": 0,
    "TeamSeason": 0,
    "ShortName": "",
    "Nationality": "England",
    "Sex": "M",
    "BioPage": "",
    "Born": "2006-09-14",
    "Twitter": "",
    "SurnameFirst": false,
    "License": "",
    "Club": "",
    "URL": "",
    "Photo": "",
    "PhotoSource": "",
    "FirstSeasonAsPro": 2023,
    "LastSeasonAsPro": 0,
    "Info": "",
    "NumRankingTitles": 0,
    "NumMaximums": 0,
    "Died": ""
  },
  {
    "ID": 2778,
    "Type": 1,
    "FirstName": "Liam",
    "MiddleName": "",
    "LastName": "Pullen",
    "TeamName": "",
    "TeamNumber": 0,
    "TeamSeason": 0,
    "ShortName": "",
    "Nationality": "England",
    "Sex": "M",
    "BioPage": "",
    "Born": "2005-07-11",
    "Twitter": "",
    "SurnameFirst": false,
    "License": "",
    "Club": "",
    "URL": "",
    "Photo": "",
    "PhotoSource": "",
    "FirstSeasonAsPro": 2023,
    "LastSeasonAsPro": 0,
    "Info": "",
    "NumRankingTitles": 0,
    "NumMaximums": 0,
    "Died": ""
  },
  {
    "ID": 2911,
    "Type": 1,
    "FirstName": "Kok Leong",
    "MiddleName": "",
    "LastName": "Lim",
    "TeamName": "",
    "TeamNumber": 0,
    "TeamSeason": 0,
    "ShortName": "Lim Kok Leong",
    "Nationality": "Malaysia",
    "Sex": "M",
    "BioPage": "",
    "Born": "1995-05-17",
    "Twitter": "",
    "SurnameFirst": true,
    "License": "",
    "Club": "",
    "URL": "",
    "Photo": "",
    "PhotoSource": "",
    "FirstSeasonAsPro": 2024,
    "LastSeasonAsPro": 0,
    "Info": "6-red champion, 2021 Southeast Asian Games",
    "NumRankingTitles": 0,
    "NumMaximums": 0,
    "Died": ""
  },
  {
    "ID": 2931,
    "Type": 1,
    "FirstName": "Haris",
    "MiddleName": "",
    "LastName": "Tahir",
    "TeamName": "",
    "TeamNumber": 0,
    "TeamSeason": 0,
    "ShortName": "",
    "Nationality": "Pakistan",
    "Sex": "M",
    "BioPage": "",
    "Born": "2000-04-09",
    "Twitter": "",
    "SurnameFirst": false,
    "License": "",
    "Club": "",
    "URL": "https://www.facebook.com/haristahirsnooker/",
    "Photo": "",
    "PhotoSource": "",
    "FirstSeasonAsPro": 2024,
    "LastSeasonAsPro": 0,
    "Info": "",
    "NumRankingTitles": 0,
    "NumMaximums": 0,
    "Died": ""
  },
  {
    "ID": 3534,
    "Type": 1,
    "FirstName": "Artemijs",
    "MiddleName": "",
    "LastName": "Zizins",
    "TeamName": "",
    "TeamNumber": 0,
    "TeamSeason": 0,
    "ShortName": "",
    "Nationality": "Latvia",
    "Sex": "M",
    "BioPage": "",
    "Born": "2006-06-02",
    "Twitter": "",
    "SurnameFirst": false,
    "License": "",
    "Club": "",
    "URL": "",
    "Photo": "https://snooker.org/img/players/Zizins-1.JPG",
    "PhotoSource": "Marian",
    "FirstSeasonAsPro": 2024,
    "LastSeasonAsPro": 0,
    "Info": "",
    "NumRankingTitles": 0,
    "NumMaximums": 0,
    "Died": ""
  },
  {
    "ID": 4153,
    "Type": 1,
    "FirstName": "Jonas",
    "MiddleName": "",
    "LastName": "Luz",
    "TeamName": "",
    "TeamNumber": 0,
    "TeamSeason": 0,
    "ShortName": "",
    "Nationality": "Brazil",
    "Sex": "M",
    "BioPage": "",
    "Born": "1985-11-29",
    "Twitter": "",
    "SurnameFirst": false,
    "License": "",
    "Club": "",
    "URL": "",
    "Photo": "",
    "PhotoSource": "",
    "FirstSeasonAsPro": 2024,
    "LastSeasonAsPro": 0,
    "Info": "",
    "NumRankingTitles": 0,
    "NumMaximums": 0,
    "Died": ""
  }
]